quarter_lib/__init__.py
quarter_lib/app.py
quarter_lib/akeyless/__init__.py
quarter_lib/database/__init__.py
quarter_lib/database/mysql/__init__.py
quarter_lib/database/timer/__init__.py
quarter_lib/file_helper/__init__.py
quarter_lib/google_calendar/__init__.py
quarter_lib/logging/__init__.py
quarter_lib/models/__init__.py
quarter_lib/monica/__init__.py
quarter_lib/notion/__init__.py
quarter_lib/todoist/__init__.py
quarter_lib/transcriber/__init__.py
quarter_lib/voice_recorder/__init__.py
quarter_lib-0.0.37.dist-info/licenses/LICENSE
quarter_lib-0.0.37.dist-info/METADATA
quarter_lib-0.0.37.dist-info/WHEEL
quarter_lib-0.0.37.dist-info/top_level.txt
quarter_lib-0.0.37.dist-info/RECORD
