Metadata-Version: 2.4
Name: quarter_lib
Version: 0.0.37
Summary: TBD
Author-email: Janik Viertel <janik.viertel@outlook.com>
Maintainer-email: Janik Viertel <janik.viertel@outlook.com>
License-Expression: MIT
Project-URL: Repository, https://github.com/viertel97/quarter-lib
Project-URL: Changelog, https://github.com/viertel97/quarter-lib/releases
Classifier: Programming Language :: Python :: 3
Classifier: Intended Audience :: Developers
Requires-Python: >=3.6
License-File: LICENSE
Requires-Dist: requests
Requires-Dist: loguru
Requires-Dist: python-dotenv
Requires-Dist: pydantic
Requires-Dist: google-auth-oauthlib==1.2.2
Requires-Dist: google-auth==2.40.3
Requires-Dist: google-api-python-client==2.178.0
Requires-Dist: todoist-api-python==3.1.0
Requires-Dist: PyMySQL==1.0.2
Requires-Dist: SpeechRecognition==3.14.3
Dynamic: license-file
